{
    "homeTeam": {
        "name": "Rockets",
        "score": 97,
        "logo": "https://cdn.nba.com/logos/nba/1610612745/primary/L/logo.svg"
    },
    "awayTeam": {
        "name": "Suns",
        "score": 88,
        "logo": "https://cdn.nba.com/logos/nba/1610612756/primary/L/logo.svg"
    },
    "game_id": "21300271",
    "date": "2013-12-04",
    "status": "Final",
    "players": {
        "2730": "Dwight Howard",
        "101128": "Francisco Garcia",
        "201166": "Aaron Brooks",
        "201935": "James Harden",
        "201956": "Omri Casspi",
        "201976": "Patrick Beverley",
        "202700": "Donatas Motiejunas",
        "203093": "Terrence Jones",
        "101112": "Channing Frye",
        "101123": "Gerald Green",
        "200782": "P.J. Tucker",
        "201609": "Goran Dragic",
        "202339": "Eric Bledsoe",
        "202693": "Markieff Morris",
        "202694": "Marcus Morris Sr.",
        "203101": "Miles Plumlee",
        "203139": "Viacheslav Kravtsov",
        "203462": "Archie Goodwin"
    },
    "starter_on": "2730|101128|201935|201976|203093|101112|200782|201609|202339|203101"
}