{
    "homeTeam": {
        "name": "Nets",
        "score": 103,
        "logo": "https://cdn.nba.com/logos/nba/1610612751/primary/L/logo.svg"
    },
    "awayTeam": {
        "name": "Pacers",
        "score": 86,
        "logo": "https://cdn.nba.com/logos/nba/1610612754/primary/L/logo.svg"
    },
    "game_id": "21300410",
    "date": "2013-12-23",
    "status": "Final",
    "players": {
        "708": "Kevin Garnett",
        "1718": "Paul Pierce",
        "1891": "Jason Terry",
        "2207": "Joe Johnson",
        "2733": "Shaun Livingston",
        "101114": "Deron Williams",
        "101154": "Andray Blatche",
        "101187": "Alan Anderson",
        "203141": "Mirza Teletovic",
        "203486": "Mason Plumlee",
        "2446": "Rasual Butler",
        "2449": "Luis Scola",
        "2561": "David West",
        "101122": "Danny Granger",
        "101133": "Ian Mahinmi",
        "201228": "C.J. Watson",
        "201579": "Roy Hibbert",
        "201588": "George Hill",
        "202331": "Paul George",
        "202362": "Lance Stephenson",
        "202388": "Donald Sloan",
        "203111": "Orlando Johnson",
        "203142": "Chris Copeland"
    },
    "starter_on": "708|2207|101114|101187|203141|2561|201579|201588|202331|202362"
}