{
    "homeTeam": {
        "name": "Knicks",
        "score": 95,
        "logo": "https://cdn.nba.com/logos/nba/1610612752/primary/L/logo.svg"
    },
    "awayTeam": {
        "name": "Raptors",
        "score": 83,
        "logo": "https://cdn.nba.com/logos/nba/1610612761/primary/L/logo.svg"
    },
    "game_id": "21300430",
    "date": "2013-12-27",
    "status": "Final",
    "players": {
        "1897": "Metta World Peace",
        "2030": "Kenyon Martin",
        "2199": "Tyson Chandler",
        "2405": "Amar'e Stoudemire",
        "2747": "JR Smith",
        "2757": "Beno Udrih",
        "200745": "Andrea Bargnani",
        "202697": "Iman Shumpert",
        "203315": "Toure' Murry",
        "203501": "Tim Hardaway Jr.",
        "2422": "John Salmons",
        "101161": "Amir Johnson",
        "200768": "Kyle Lowry",
        "201942": "DeMar DeRozan",
        "201946": "Tyler Hansbrough",
        "202335": "Patrick Patterson",
        "202349": "Greivis Vasquez",
        "202685": "Jonas Valanciunas",
        "203082": "Terrence Ross"
    },
    "starter_on": "2199|2747|2757|200745|202697|101161|200768|201942|202685|203082"
}