{
    "homeTeam": {
        "name": "Bucks",
        "score": 114,
        "logo": "https://cdn.nba.com/logos/nba/1610612749/primary/L/logo.svg"
    },
    "awayTeam": {
        "name": "Clippers",
        "score": 86,
        "logo": "https://cdn.nba.com/logos/nba/1610612746/primary/L/logo.svg"
    },
    "game_id": "21300665",
    "date": "2014-01-27",
    "status": "Final",
    "players": {
        "2037": "Jamal Crawford",
        "2045": "Hedo Turkoglu",
        "2440": "Matt Barnes",
        "2584": "Willie Green",
        "200755": "JJ Redick",
        "200797": "Ryan Hollins",
        "201162": "Jared Dudley",
        "201599": "DeAndre Jordan",
        "201933": "Blake Griffin",
        "201954": "Darren Collison",
        "201957": "Byron Mullens",
        "203493": "Reggie Bullock Jr.",
        "2406": "Caron Butler",
        "2557": "Luke Ridnour",
        "101141": "Ersan Ilyasova",
        "202688": "Brandon Knight",
        "203089": "John Henson",
        "203114": "Khris Middleton",
        "203489": "Nate Wolters",
        "203507": "Giannis Antetokounmpo",
        "203545": "Miroslav Raduljica"
    },
    "starter_on": "2440|200755|201599|201933|201954|101141|202688|203089|203114|203507"
}