{
    "homeTeam": {
        "name": "Pistons",
        "score": 102,
        "logo": "https://cdn.nba.com/logos/nba/1610612765/primary/L/logo.svg"
    },
    "awayTeam": {
        "name": "Cavaliers",
        "score": 93,
        "logo": "https://cdn.nba.com/logos/nba/1610612739/primary/L/logo.svg"
    },
    "game_id": "21400839",
    "date": "2015-02-24",
    "status": "Final",
    "players": {
        "2544": "LeBron James",
        "2570": "Kendrick Perkins",
        "2592": "James Jones",
        "2747": "JR Smith",
        "201567": "Kevin Love",
        "202389": "Timofey Mozgov",
        "202681": "Kyrie Irving",
        "202684": "Tristan Thompson",
        "202697": "Iman Shumpert",
        "203521": "Matthew Dellavedova",
        "203925": "Joe Harris",
        "2406": "Caron Butler",
        "2419": "Tayshaun Prince",
        "101249": "John Lucas III",
        "201229": "Anthony Tolliver",
        "201975": "Jodie Meeks",
        "202328": "Greg Monroe",
        "202704": "Reggie Jackson",
        "203083": "Andre Drummond",
        "203484": "Kentavious Caldwell-Pope",
        "203915": "Spencer Dinwiddie"
    },
    "starter_on": "2544|2747|201567|202389|202681|2419|202328|202704|203083|203484"
}