{
    "homeTeam": {
        "name": "Mavericks",
        "score": 82,
        "logo": "https://cdn.nba.com/logos/nba/1610612742/primary/L/logo.svg"
    },
    "awayTeam": {
        "name": "Jazz",
        "score": 87,
        "logo": "https://cdn.nba.com/logos/nba/1610612762/primary/L/logo.svg"
    },
    "game_id": "21400797",
    "date": "2015-02-11",
    "status": "Final",
    "players": {
        "1717": "Dirk Nowitzki",
        "2210": "Richard Jefferson",
        "2734": "Devin Harris",
        "101111": "Charlie Villanueva",
        "101145": "Monta Ellis",
        "200826": "J.J. Barea",
        "202329": "Al-Farouq Aminu",
        "202718": "Chandler Parsons",
        "202962": "Greg Smith",
        "203108": "Bernard James",
        "200779": "Steve Novak",
        "202324": "Derrick Favors",
        "202330": "Gordon Hayward",
        "202344": "Trevor Booker",
        "202407": "Elijah Millsap",
        "202683": "Enes Freedom",
        "203497": "Rudy Gobert",
        "203504": "Trey Burke",
        "203546": "Ian Clark",
        "203957": "Dante Exum"
    },
    "starter_on": "1717|101145|200826|202718|202962|202324|202330|202407|202683|203957"
}