{
    "homeTeam": {
        "name": "Clippers",
        "score": 84,
        "logo": "https://cdn.nba.com/logos/nba/1610612746/primary/L/logo.svg"
    },
    "awayTeam": {
        "name": "Suns",
        "score": 124,
        "logo": "https://cdn.nba.com/logos/nba/1610612756/primary/L/logo.svg"
    },
    "game_id": "21500839",
    "date": "2016-02-22",
    "status": "Final",
    "players": {
        "1718": "Paul Pierce",
        "2037": "Jamal Crawford",
        "101108": "Chris Paul",
        "200755": "JJ Redick",
        "201145": "Jeff Green",
        "201599": "DeAndre Jordan",
        "201601": "Luc Mbah a Moute",
        "202325": "Wesley Johnson",
        "202332": "Cole Aldrich",
        "203143": "Pablo Prigioni",
        "203912": "C.J. Wilcox",
        "1627293": "Alex Stepheson",
        "2743": "Kris Humphries",
        "101179": "Ronnie Price",
        "200782": "P.J. Tucker",
        "201603": "Sonny Weems",
        "202720": "Jon Leuer",
        "203141": "Mirza Teletovic",
        "203458": "Alex Len",
        "203462": "Archie Goodwin",
        "203515": "Phil Pressey",
        "1626164": "Devin Booker"
    },
    "starter_on": "1718|101108|200755|201599|201601|2743|101179|200782|203458|1626164"
}