{
    "homeTeam": {
        "name": "Spurs",
        "score": 79,
        "logo": "https://cdn.nba.com/logos/nba/1610612759/primary/L/logo.svg"
    },
    "awayTeam": {
        "name": "Suns",
        "score": 112,
        "logo": "https://cdn.nba.com/logos/nba/1610612756/primary/L/logo.svg"
    },
    "game_id": "21500481",
    "date": "2015-12-30",
    "status": "Final",
    "players": {
        "2199": "Tyson Chandler",
        "200782": "P.J. Tucker",
        "201603": "Sonny Weems",
        "202688": "Brandon Knight",
        "202693": "Markieff Morris",
        "202720": "Jon Leuer",
        "203141": "Mirza Teletovic",
        "203458": "Alex Len",
        "203462": "Archie Goodwin",
        "203928": "Cory Jefferson",
        "203933": "T.J. Warren",
        "203955": "Bryce Cotton",
        "1626164": "Devin Booker",
        "1938": "Manu Ginobili",
        "2225": "Tony Parker",
        "2561": "David West",
        "2564": "Boris Diaw",
        "2588": "Matt Bonner",
        "200746": "LaMarcus Aldridge",
        "201980": "Danny Green",
        "201988": "Patty Mills",
        "202695": "Kawhi Leonard",
        "203492": "Ray McCallum",
        "203613": "Jonathon Simmons",
        "203937": "Kyle Anderson",
        "1626246": "Boban Marjanovic"
    },
    "starter_on": "200782|202688|202720|203458|1626164|2225|2561|200746|201980|202695"
}