{
    "homeTeam": {
        "name": "Lakers",
        "score": 95,
        "logo": "https://cdn.nba.com/logos/nba/1610612747/primary/L/logo.svg"
    },
    "awayTeam": {
        "name": "Warriors",
        "score": 112,
        "logo": "https://cdn.nba.com/logos/nba/1610612744/primary/L/logo.svg"
    },
    "game_id": "21500931",
    "date": "2016-03-06",
    "status": "Final",
    "players": {
        "2571": "Leandro Barbosa",
        "2733": "Shaun Livingston",
        "2760": "Anderson Varejao",
        "101106": "Andrew Bogut",
        "201575": "Brandon Rush",
        "201578": "Marreese Speights",
        "201939": "Stephen Curry",
        "202691": "Klay Thompson",
        "203084": "Harrison Barnes",
        "203110": "Draymond Green",
        "203546": "Ian Clark",
        "203949": "James Michael McAdoo",
        "977": "Kobe Bryant",
        "1897": "Metta World Peace",
        "101138": "Brandon Bass",
        "201156": "Nick Young",
        "201579": "Roy Hibbert",
        "203903": "Jordan Clarkson",
        "203944": "Julius Randle",
        "1626156": "D'Angelo Russell",
        "1626204": "Larry Nance Jr.",
        "1626273": "Marcelo Huertas"
    },
    "starter_on": "101106|201939|202691|203084|203110|977|201579|203903|203944|1626156"
}