{
    "homeTeam": {
        "name": "Nets",
        "score": 129,
        "logo": "https://cdn.nba.com/logos/nba/1610612751/primary/L/logo.svg"
    },
    "awayTeam": {
        "name": "Trail Blazers",
        "score": 109,
        "logo": "https://cdn.nba.com/logos/nba/1610612757/primary/L/logo.svg"
    },
    "game_id": "21600194",
    "date": "2016-11-20",
    "status": "Final",
    "players": {
        "2449": "Luis Scola",
        "200751": "Randy Foye",
        "201572": "Brook Lopez",
        "202344": "Trevor Booker",
        "202711": "Bojan Bogdanovic",
        "203120": "Justin Hamilton",
        "203461": "Anthony Bennett",
        "203925": "Joe Harris",
        "203930": "Sean Kilpatrick",
        "1626178": "Rondae Hollis-Jefferson",
        "1627785": "Isaiah Whitehead",
        "1627812": "Yogi Ferrell",
        "202323": "Evan Turner",
        "202334": "Ed Davis",
        "203081": "Damian Lillard",
        "203086": "Meyers Leonard",
        "203090": "Maurice Harkless",
        "203459": "Allen Crabbe",
        "203468": "CJ McCollum",
        "203486": "Mason Plumlee",
        "203894": "Shabazz Napier",
        "203943": "Noah Vonleh",
        "1626192": "Pat Connaughton",
        "1627774": "Jake Layman",
        "1627817": "Tim Quarterman"
    },
    "starter_on": "201572|202344|202711|1626178|1627785|202334|203081|203090|203468|203486"
}