{
    "homeTeam": {
        "name": "Cavaliers",
        "score": 110,
        "logo": "https://cdn.nba.com/logos/nba/1610612739/primary/L/logo.svg"
    },
    "awayTeam": {
        "name": "Hawks",
        "score": 106,
        "logo": "https://cdn.nba.com/logos/nba/1610612737/primary/L/logo.svg"
    },
    "game_id": "21600100",
    "date": "2016-11-08",
    "status": "Final",
    "players": {
        "2730": "Dwight Howard",
        "2743": "Kris Humphries",
        "200757": "Thabo Sefolosha",
        "200794": "Paul Millsap",
        "203145": "Kent Bazemore",
        "203471": "Dennis Schroder",
        "203488": "Mike Muscala",
        "203501": "Tim Hardaway Jr.",
        "1627098": "Malcolm Delaney",
        "1627752": "Taurean Prince",
        "2210": "Richard Jefferson",
        "2399": "Mike Dunleavy",
        "2544": "LeBron James",
        "2747": "JR Smith",
        "101112": "Channing Frye",
        "201567": "Kevin Love",
        "202681": "Kyrie Irving",
        "202684": "Tristan Thompson",
        "202697": "Iman Shumpert"
    },
    "starter_on": "2730|200757|200794|203145|203471|2544|2747|201567|202681|202684"
}