{
    "homeTeam": {
        "name": "Nets",
        "score": 113,
        "logo": "https://cdn.nba.com/logos/nba/1610612751/primary/L/logo.svg"
    },
    "awayTeam": {
        "name": "Bucks",
        "score": 94,
        "logo": "https://cdn.nba.com/logos/nba/1610612749/primary/L/logo.svg"
    },
    "game_id": "21800792",
    "date": "2019-02-04",
    "status": "Final",
    "players": {
        "101141": "Ersan Ilyasova",
        "201572": "Brook Lopez",
        "201588": "George Hill",
        "202339": "Eric Bledsoe",
        "203114": "Khris Middleton",
        "203503": "Tony Snell",
        "203507": "Giannis Antetokounmpo",
        "1626174": "Christian Wood",
        "1626192": "Pat Connaughton",
        "1627763": "Malcolm Brogdon",
        "1628391": "D.J. Wilson",
        "1628425": "Sterling Brown",
        "201960": "DeMarre Carroll",
        "202334": "Ed Davis",
        "203894": "Shabazz Napier",
        "1626156": "D'Angelo Russell",
        "1626178": "Rondae Hollis-Jefferson",
        "1626203": "Treveon Graham",
        "1626210": "Alan Williams",
        "1628249": "Mitchell Creek",
        "1628386": "Jarrett Allen",
        "1629033": "Theo Pinson",
        "1629058": "Dzanan Musa",
        "1629066": "Rodions Kurucs"
    },
    "starter_on": "201572|202339|203114|203507|1627763|203894|1626156|1626203|1628386|1629066"
}