{
    "homeTeam": {
        "name": "Raptors",
        "score": 98,
        "logo": "https://cdn.nba.com/logos/nba/1610612761/primary/L/logo.svg"
    },
    "awayTeam": {
        "name": "Lakers",
        "score": 111,
        "logo": "https://cdn.nba.com/logos/nba/1610612747/primary/L/logo.svg"
    },
    "game_id": "21801023",
    "date": "2019-03-14",
    "status": "Final",
    "players": {
        "2544": "LeBron James",
        "200765": "Rajon Rondo",
        "201281": "Andre Ingram",
        "201580": "JaVale McGee",
        "203484": "Kentavious Caldwell-Pope",
        "203488": "Mike Muscala",
        "203493": "Reggie Bullock Jr.",
        "1627936": "Alex Caruso",
        "1628398": "Kyle Kuzma",
        "1628404": "Josh Hart",
        "1629021": "Moritz Wagner",
        "1629140": "Johnathan Williams",
        "201188": "Marc Gasol",
        "201980": "Danny Green",
        "202391": "Jeremy Lin",
        "202695": "Kawhi Leonard",
        "203961": "Eric Moreland",
        "1626181": "Norman Powell",
        "1626259": "Malcolm Miller",
        "1627775": "Patrick McCaw",
        "1627783": "Pascal Siakam",
        "1628070": "Jordan Loyd",
        "1628384": "OG Anunoby",
        "1628449": "Chris Boucher"
    },
    "starter_on": "2544|200765|201580|203493|1628398|201188|201980|202391|202695|1627783"
}