{
    "homeTeam": {
        "name": "Grizzlies",
        "score": 122,
        "logo": "https://cdn.nba.com/logos/nba/1610612763/primary/L/logo.svg"
    },
    "awayTeam": {
        "name": "Raptors",
        "score": 114,
        "logo": "https://cdn.nba.com/logos/nba/1610612761/primary/L/logo.svg"
    },
    "game_id": "21800303",
    "date": "2018-11-27",
    "status": "Final",
    "players": {
        "101139": "CJ Miles",
        "200768": "Kyle Lowry",
        "201586": "Serge Ibaka",
        "201980": "Danny Green",
        "202685": "Jonas Valanciunas",
        "202695": "Kawhi Leonard",
        "203485": "Lorenzo Brown",
        "1626153": "Delon Wright",
        "1627783": "Pascal Siakam",
        "1627832": "Fred VanVleet",
        "1628384": "OG Anunoby",
        "201144": "Mike Conley",
        "201188": "Marc Gasol",
        "201956": "Omri Casspi",
        "202066": "Garrett Temple",
        "202714": "Shelvin Mack",
        "203210": "JaMychal Green",
        "203937": "Kyle Anderson",
        "1627782": "Wayne Selden",
        "1628991": "Jaren Jackson Jr."
    },
    "starter_on": "200768|201586|201980|202695|1627783|201144|201188|202066|203937|1628991"
}