{
    "homeTeam": {
        "name": "Spurs",
        "score": 117,
        "logo": "https://cdn.nba.com/logos/nba/1610612759/primary/L/logo.svg"
    },
    "awayTeam": {
        "name": "Cavaliers",
        "score": 109,
        "logo": "https://cdn.nba.com/logos/nba/1610612739/primary/L/logo.svg"
    },
    "game_id": "21900368",
    "date": "2019-12-12",
    "status": "Final",
    "players": {
        "201567": "Kevin Love",
        "202684": "Tristan Thompson",
        "203089": "John Henson",
        "203521": "Matthew Dellavedova",
        "203903": "Jordan Clarkson",
        "1626204": "Larry Nance Jr.",
        "1626224": "Cedi Osman",
        "1629012": "Collin Sexton",
        "1629636": "Darius Garland",
        "1629645": "Kevin Porter Jr.",
        "200746": "LaMarcus Aldridge",
        "200752": "Rudy Gay",
        "201158": "Marco Belinelli",
        "201942": "DeMar DeRozan",
        "201988": "Patty Mills",
        "1626168": "Trey Lyles",
        "1627749": "Dejounte Murray",
        "1627751": "Jakob Poeltl",
        "1627854": "Bryn Forbes",
        "1628401": "Derrick White",
        "1629022": "Lonnie Walker IV"
    },
    "starter_on": "201567|202684|1626224|1629012|1629636|200746|200752|201942|1627854|1628401"
}