{
    "homeTeam": {
        "name": "Jazz",
        "score": 96,
        "logo": "https://cdn.nba.com/logos/nba/1610612762/primary/L/logo.svg"
    },
    "awayTeam": {
        "name": "Clippers",
        "score": 110,
        "logo": "https://cdn.nba.com/logos/nba/1610612746/primary/L/logo.svg"
    },
    "game_id": "21900063",
    "date": "2019-10-30",
    "status": "Final",
    "players": {
        "101150": "Lou Williams",
        "201976": "Patrick Beverley",
        "202335": "Patrick Patterson",
        "203090": "Maurice Harkless",
        "203210": "JaMychal Green",
        "203585": "Rodney McGruder",
        "1626149": "Montrezl Harrell",
        "1627826": "Ivica Zubac",
        "1628476": "Derrick Walton Jr.",
        "1629010": "Jerome Robinson",
        "1629013": "Landry Shamet",
        "1629611": "Terance Mann",
        "1629662": "Mfiondu Kabengele",
        "201144": "Mike Conley",
        "201145": "Jeff Green",
        "202334": "Ed Davis",
        "202711": "Bojan Bogdanovic",
        "203497": "Rudy Gobert",
        "204060": "Joe Ingles",
        "1626144": "Emmanuel Mudiay",
        "1626220": "Royce O'Neale",
        "1627777": "Georges Niang",
        "1628378": "Donovan Mitchell",
        "1628396": "Tony Bradley",
        "1628430": "Nigel Williams-Goss",
        "1629742": "Stanton Kidd"
    },
    "starter_on": "101150|201976|202335|1627826|1629013|201144|202711|203497|1626220|1628378"
}