{
    "homeTeam": {
        "name": "Mavericks",
        "score": 94,
        "logo": "https://cdn.nba.com/logos/nba/1610612742/primary/L/logo.svg"
    },
    "awayTeam": {
        "name": "Warriors",
        "score": 142,
        "logo": "https://cdn.nba.com/logos/nba/1610612744/primary/L/logo.svg"
    },
    "game_id": "21900208",
    "date": "2019-11-20",
    "status": "Final",
    "players": {
        "201584": "Courtney Lee",
        "203501": "Tim Hardaway Jr.",
        "203939": "Dwight Powell",
        "204001": "Kristaps Porzingis",
        "1626153": "Delon Wright",
        "1626246": "Boban Marjanovic",
        "1627827": "Dorian Finney-Smith",
        "1628382": "Justin Jackson",
        "1628467": "Maxi Kleber",
        "1628973": "Jalen Brunson",
        "1629029": "Luka Doncic",
        "1629151": "Ryan Broekhoff",
        "202692": "Alec Burks",
        "203922": "Glenn Robinson III",
        "1626161": "Willie Cauley-Stein",
        "1627737": "Marquese Chriss",
        "1629016": "Omari Spellman",
        "1629065": "Ky Bowman",
        "1629672": "Eric Paschall",
        "1629673": "Jordan Poole"
    },
    "starter_on": "203501|203939|204001|1627827|1629029|202692|203922|1626161|1629065|1629672"
}