{
    "homeTeam": {
        "name": "Pacers",
        "score": 124,
        "logo": "https://cdn.nba.com/logos/nba/1610612754/primary/L/logo.svg"
    },
    "awayTeam": {
        "name": "Pelicans",
        "score": 117,
        "logo": "https://cdn.nba.com/logos/nba/1610612740/primary/L/logo.svg"
    },
    "game_id": "21900780",
    "date": "2020-02-08",
    "status": "Final",
    "players": {
        "200755": "JJ Redick",
        "201950": "Jrue Holiday",
        "202324": "Derrick Favors",
        "202734": "E'Twaun Moore",
        "1626143": "Jahlil Okafor",
        "1628366": "Lonzo Ball",
        "1628402": "Frank Jackson",
        "1628404": "Josh Hart",
        "1629637": "Jaxson Hayes",
        "1629740": "Nicolo Melli",
        "203087": "Jeremy Lamb",
        "203200": "Justin Holiday",
        "203926": "Doug McDermott",
        "203933": "T.J. Warren",
        "204456": "T.J. McConnell",
        "1626167": "Myles Turner",
        "1627734": "Domantas Sabonis",
        "1627763": "Malcolm Brogdon",
        "1628410": "Edmond Sumner",
        "1628988": "Aaron Holiday",
        "1629048": "Goga Bitadze"
    },
    "starter_on": "201950|202324|1628366|1628404|1629740|203087|203933|1626167|1627734|1627763"
}