{
    "homeTeam": {
        "name": "Mavericks",
        "score": 78,
        "logo": "https://cdn.nba.com/logos/nba/1610612742/primary/L/logo.svg"
    },
    "awayTeam": {
        "name": "Thunder",
        "score": 87,
        "logo": "https://cdn.nba.com/logos/nba/1610612760/primary/L/logo.svg"
    },
    "game_id": "22000549",
    "date": "2021-03-03",
    "status": "Final",
    "players": {
        "201949": "James Johnson",
        "203501": "Tim Hardaway Jr.",
        "203504": "Trey Burke",
        "203939": "Dwight Powell",
        "204001": "Kristaps Porzingis",
        "1626196": "Josh Richardson",
        "1627827": "Dorian Finney-Smith",
        "1628411": "Wes Iwundu",
        "1628467": "Maxi Kleber",
        "1628973": "Jalen Brunson",
        "201143": "Al Horford",
        "203488": "Mike Muscala",
        "1628382": "Justin Jackson",
        "1628983": "Shai Gilgeous-Alexander",
        "1629026": "Kenrich Williams",
        "1629647": "Darius Bazley",
        "1629652": "Luguentz Dort",
        "1629660": "Ty Jerome",
        "1629676": "Isaiah Roby",
        "1630177": "Theo Maledon"
    },
    "starter_on": "204001|1626196|1627827|1628467|1628973|201143|1628983|1629647|1629652|1630177"
}