{
    "homeTeam": {
        "name": "Thunder",
        "score": 129,
        "logo": "https://cdn.nba.com/logos/nba/1610612760/primary/L/logo.svg"
    },
    "awayTeam": {
        "name": "Cavaliers",
        "score": 102,
        "logo": "https://cdn.nba.com/logos/nba/1610612739/primary/L/logo.svg"
    },
    "game_id": "22000785",
    "date": "2021-04-08",
    "status": "Final",
    "players": {
        "201567": "Kevin Love",
        "203521": "Matthew Dellavedova",
        "1627752": "Taurean Prince",
        "1628392": "Isaiah Hartenstein",
        "1629012": "Collin Sexton",
        "1629636": "Darius Garland",
        "1629731": "Dean Wade",
        "1630171": "Isaac Okoro",
        "1630205": "Lamar Stevens",
        "1630271": "Brodric Thomas",
        "1628396": "Tony Bradley",
        "1629004": "Svi Mykhailiuk",
        "1629026": "Kenrich Williams",
        "1629620": "Justin Robinson",
        "1629650": "Moses Brown",
        "1629658": "Jaylen Hoard",
        "1629660": "Ty Jerome",
        "1630177": "Theo Maledon",
        "1630197": "Aleksej Pokusevski"
    },
    "starter_on": "201567|1629012|1629636|1629731|1630171|1629004|1629026|1629650|1630177|1630197"
}