{
    "homeTeam": {
        "name": "Pelicans",
        "score": 103,
        "logo": "https://cdn.nba.com/logos/nba/1610612740/primary/L/logo.svg"
    },
    "awayTeam": {
        "name": "Mavericks",
        "score": 112,
        "logo": "https://cdn.nba.com/logos/nba/1610612742/primary/L/logo.svg"
    },
    "game_id": "22000698",
    "date": "2021-03-27",
    "status": "Final",
    "players": {
        "202339": "Eric Bledsoe",
        "203500": "Steven Adams",
        "1626195": "Willy Hernangomez",
        "1627742": "Brandon Ingram",
        "1628404": "Josh Hart",
        "1629627": "Zion Williamson",
        "1629638": "Nickeil Alexander-Walker",
        "1630184": "Kira Lewis Jr.",
        "1630230": "Naji Marshall",
        "203501": "Tim Hardaway Jr.",
        "203504": "Trey Burke",
        "203939": "Dwight Powell",
        "1626196": "Josh Richardson",
        "1626246": "Boban Marjanovic",
        "1627827": "Dorian Finney-Smith",
        "1628467": "Maxi Kleber",
        "1628973": "Jalen Brunson"
    },
    "starter_on": "202339|203500|1627742|1629627|1629638|1626196|1626246|1627827|1628467|1628973"
}