{
    "homeTeam": {
        "name": "Bulls",
        "score": 120,
        "logo": "https://cdn.nba.com/logos/nba/1610612741/primary/L/logo.svg"
    },
    "awayTeam": {
        "name": "Jazz",
        "score": 95,
        "logo": "https://cdn.nba.com/logos/nba/1610612762/primary/L/logo.svg"
    },
    "game_id": "22000656",
    "date": "2021-03-22",
    "status": "Final",
    "players": {
        "201152": "Thaddeus Young",
        "203107": "Tomas Satoransky",
        "203490": "Otto Porter Jr.",
        "203897": "Zach LaVine",
        "1626245": "Cristiano Felicio",
        "1627756": "Denzel Valentine",
        "1627853": "Ryan Arcidiacono",
        "1628374": "Lauri Markkanen",
        "1628436": "Luke Kornet",
        "1628976": "Wendell Carter Jr.",
        "1629632": "Coby White",
        "1629655": "Daniel Gafford",
        "1629690": "Adam Mokoka",
        "1630172": "Patrick Williams",
        "101141": "Ersan Ilyasova",
        "201144": "Mike Conley",
        "202324": "Derrick Favors",
        "202711": "Bojan Bogdanovic",
        "203497": "Rudy Gobert",
        "203903": "Jordan Clarkson",
        "204060": "Joe Ingles",
        "1626220": "Royce O'Neale",
        "1627777": "Georges Niang",
        "1628378": "Donovan Mitchell",
        "1629671": "Miye Oni",
        "1629714": "Jarrell Brantley",
        "1629752": "Juwan Morgan",
        "1630235": "Trent Forrest"
    },
    "starter_on": "201152|203107|203897|1628374|1630172|201144|202711|203497|1626220|1628378"
}