{
    "homeTeam": {
        "name": "Lakers",
        "score": 93,
        "logo": "https://cdn.nba.com/logos/nba/1610612747/primary/L/logo.svg"
    },
    "awayTeam": {
        "name": "Magic",
        "score": 96,
        "logo": "https://cdn.nba.com/logos/nba/1610612753/primary/L/logo.svg"
    },
    "game_id": "22000706",
    "date": "2021-03-28",
    "status": "Final",
    "players": {
        "201188": "Marc Gasol",
        "202083": "Wesley Matthews",
        "202693": "Markieff Morris",
        "203471": "Dennis Schroder",
        "203484": "Kentavious Caldwell-Pope",
        "1626149": "Montrezl Harrell",
        "1627936": "Alex Caruso",
        "1628398": "Kyle Kuzma",
        "1629659": "Talen Horton-Tucker",
        "203487": "Michael Carter-Williams",
        "203490": "Otto Porter Jr.",
        "203516": "James Ennis III",
        "203920": "Khem Birch",
        "1626184": "Chasson Randle",
        "1628407": "Dwayne Bacon",
        "1628964": "Mo Bamba",
        "1628976": "Wendell Carter Jr.",
        "1629643": "Chuma Okeke",
        "1630181": "R.J. Hampton",
        "1630211": "Karim Mane"
    },
    "starter_on": "201188|202693|203471|203484|1628398|203487|203516|203920|1628407|1629643"
}