{
    "homeTeam": {
        "name": "Thunder",
        "score": 110,
        "logo": "https://cdn.nba.com/logos/nba/1610612760/primary/L/logo.svg"
    },
    "awayTeam": {
        "name": "Warriors",
        "score": 98,
        "logo": "https://cdn.nba.com/logos/nba/1610612744/primary/L/logo.svg"
    },
    "game_id": "22100813",
    "date": "2022-02-07",
    "status": "Final",
    "players": {
        "2738": "Andre Iguodala",
        "201939": "Stephen Curry",
        "202691": "Klay Thompson",
        "203490": "Otto Porter Jr.",
        "203952": "Andrew Wiggins",
        "1626172": "Kevon Looney",
        "1627780": "Gary Payton II",
        "1627814": "Damion Lee",
        "1629308": "Juan Toscano-Anderson",
        "1629673": "Jordan Poole",
        "1630228": "Jonathan Kuminga",
        "1630541": "Moses Moody",
        "202324": "Derrick Favors",
        "1629026": "Kenrich Williams",
        "1629603": "Mamadi Diakite",
        "1629647": "Darius Bazley",
        "1629652": "Luguentz Dort",
        "1629660": "Ty Jerome",
        "1630177": "Theo Maledon",
        "1630544": "Tre Mann",
        "1630581": "Josh Giddey"
    },
    "starter_on": "201939|202691|203490|203952|1626172|202324|1629647|1629652|1630544|1630581"
}