{
    "homeTeam": {
        "name": "Timberwolves",
        "score": 133,
        "logo": "https://cdn.nba.com/logos/nba/1610612750/primary/L/logo.svg"
    },
    "awayTeam": {
        "name": "76ers",
        "score": 102,
        "logo": "https://cdn.nba.com/logos/nba/1610612755/primary/L/logo.svg"
    },
    "game_id": "22100901",
    "date": "2022-02-25",
    "status": "Final",
    "players": {
        "201976": "Patrick Beverley",
        "1626156": "D'Angelo Russell",
        "1626157": "Karl-Anthony Towns",
        "1627752": "Taurean Prince",
        "1627774": "Jake Layman",
        "1629006": "Josh Okogie",
        "1629020": "Jarred Vanderbilt",
        "1629162": "Jordan McLaughlin",
        "1629669": "Jaylen Nowell",
        "1629675": "Naz Reid",
        "1630162": "Anthony Edwards",
        "1630183": "Jaden McDaniels",
        "200794": "Paul Millsap",
        "201935": "James Harden",
        "201980": "Danny Green",
        "202699": "Tobias Harris",
        "203954": "Joel Embiid",
        "1626161": "Willie Cauley-Stein",
        "1627777": "Georges Niang",
        "1627788": "Furkan Korkmaz",
        "1629003": "Shake Milton",
        "1629680": "Matisse Thybulle",
        "1630178": "Tyrese Maxey",
        "1630194": "Paul Reed",
        "1630198": "Isaiah Joe"
    },
    "starter_on": "201976|1626156|1626157|1629020|1630162|201935|202699|203954|1629680|1630178"
}