{
    "homeTeam": {
        "name": "Nets",
        "score": 110,
        "logo": "https://cdn.nba.com/logos/nba/1610612751/primary/L/logo.svg"
    },
    "awayTeam": {
        "name": "Knicks",
        "score": 112,
        "logo": "https://cdn.nba.com/logos/nba/1610612752/primary/L/logo.svg"
    },
    "game_id": "22100314",
    "date": "2021-11-30",
    "status": "Final",
    "players": {
        "200746": "LaMarcus Aldridge",
        "200794": "Paul Millsap",
        "201142": "Kevin Durant",
        "201935": "James Harden",
        "201949": "James Johnson",
        "201988": "Patty Mills",
        "1627761": "DeAndre' Bembry",
        "1628971": "Bruce Brown",
        "1628975": "Jevon Carter",
        "1630560": "Cam Thomas",
        "201565": "Derrick Rose",
        "202692": "Alec Burks",
        "203095": "Evan Fournier",
        "203457": "Nerlens Noel",
        "203944": "Julius Randle",
        "1629011": "Mitchell Robinson",
        "1629628": "RJ Barrett",
        "1629656": "Quentin Grimes",
        "1630167": "Obi Toppin",
        "1630193": "Immanuel Quickley"
    },
    "starter_on": "200746|201142|201935|201988|1627761|202692|203095|203944|1629011|1629628"
}