{
    "homeTeam": {
        "name": "Bucks",
        "score": 98,
        "logo": "https://cdn.nba.com/logos/nba/1610612749/primary/L/logo.svg"
    },
    "awayTeam": {
        "name": "Cavaliers",
        "score": 113,
        "logo": "https://cdn.nba.com/logos/nba/1610612739/primary/L/logo.svg"
    },
    "game_id": "22200216",
    "date": "2022-11-16",
    "status": "Final",
    "players": {
        "201567": "Kevin Love",
        "201577": "Robin Lopez",
        "203526": "Raul Neto",
        "1626224": "Cedi Osman",
        "1627747": "Caris LeVert",
        "1628378": "Donovan Mitchell",
        "1629603": "Mamadi Diakite",
        "1629636": "Darius Garland",
        "1630171": "Isaac Okoro",
        "1630205": "Lamar Stevens",
        "1630596": "Evan Mobley",
        "1630600": "Isaiah Mobley",
        "201572": "Brook Lopez",
        "201586": "Serge Ibaka",
        "201588": "George Hill",
        "203507": "Giannis Antetokounmpo",
        "203648": "Thanasis Antetokounmpo",
        "1626171": "Bobby Portis",
        "1628975": "Jevon Carter",
        "1629670": "Jordan Nwora",
        "1630572": "Sandro Mamukelashvili",
        "1630699": "MarJon Beauchamp",
        "1631260": "AJ Green"
    },
    "starter_on": "1627747|1628378|1629636|1630205|1630596|201572|203507|1626171|1628975|1630699"
}