{
    "homeTeam": {
        "name": "Rockets",
        "score": 108,
        "logo": "https://cdn.nba.com/logos/nba/1610612745/primary/L/logo.svg"
    },
    "awayTeam": {
        "name": "Jazz",
        "score": 114,
        "logo": "https://cdn.nba.com/logos/nba/1610612762/primary/L/logo.svg"
    },
    "game_id": "22200048",
    "date": "2022-10-24",
    "status": "Final",
    "players": {
        "201569": "Eric Gordon",
        "1626246": "Boban Marjanovic",
        "1629645": "Kevin Porter Jr.",
        "1629726": "Garrison Mathews",
        "1630224": "Jalen Green",
        "1630227": "Daishen Nix",
        "1630231": "KJ Martin",
        "1630528": "Josh Christopher",
        "1630586": "Usman Garuba",
        "1631095": "Jabari Smith Jr.",
        "1631106": "Tari Eason",
        "200752": "Rudy Gay",
        "201144": "Mike Conley",
        "203482": "Kelly Olynyk",
        "203903": "Jordan Clarkson",
        "1627736": "Malik Beasley",
        "1628374": "Lauri Markkanen",
        "1629012": "Collin Sexton",
        "1629020": "Jarred Vanderbilt",
        "1629638": "Nickeil Alexander-Walker",
        "1629659": "Talen Horton-Tucker",
        "1631117": "Walker Kessler",
        "1631323": "Simone Fontecchio"
    },
    "starter_on": "201569|1629645|1630224|1630231|1631095|201144|203482|203903|1628374|1629020"
}