{
    "homeTeam": {
        "name": "Pacers",
        "score": 113,
        "logo": "https://cdn.nba.com/logos/nba/1610612754/primary/L/logo.svg"
    },
    "awayTeam": {
        "name": "Timberwolves",
        "score": 111,
        "logo": "https://cdn.nba.com/logos/nba/1610612750/primary/L/logo.svg"
    },
    "game_id": "22300903",
    "date": "2024-03-07",
    "status": "Final",
    "players": {
        "201144": "Mike Conley",
        "203497": "Rudy Gobert",
        "203933": "T.J. Warren",
        "203937": "Kyle Anderson",
        "1628420": "Monte Morris",
        "1629638": "Nickeil Alexander-Walker",
        "1629675": "Naz Reid",
        "1630162": "Anthony Edwards",
        "1630183": "Jaden McDaniels",
        "204456": "T.J. McConnell",
        "1626167": "Myles Turner",
        "1627783": "Pascal Siakam",
        "1629614": "Andrew Nembhard",
        "1630167": "Obi Toppin",
        "1630169": "Tyrese Haliburton",
        "1630174": "Aaron Nesmith",
        "1630188": "Jalen Smith",
        "1630543": "Isaiah Jackson",
        "1641716": "Jarace Walker",
        "1641767": "Ben Sheppard"
    },
    "starter_on": "201144|203497|203937|1630162|1630183|1626167|1627783|1629614|1630169|1630174"
}