{
    "homeTeam": {
        "name": "Nets",
        "score": 129,
        "logo": "https://cdn.nba.com/logos/nba/1610612751/primary/L/logo.svg"
    },
    "awayTeam": {
        "name": "Bucks",
        "score": 125,
        "logo": "https://cdn.nba.com/logos/nba/1610612749/primary/L/logo.svg"
    },
    "game_id": "22300149",
    "date": "2023-11-06",
    "status": "Final",
    "players": {
        "201572": "Brook Lopez",
        "203081": "Damian Lillard",
        "203109": "Jae Crowder",
        "203114": "Khris Middleton",
        "203507": "Giannis Antetokounmpo",
        "1626166": "Cameron Payne",
        "1626171": "Bobby Portis",
        "1626192": "Pat Connaughton",
        "1627736": "Malik Beasley",
        "1630699": "MarJon Beauchamp",
        "203915": "Spencer Dinwiddie",
        "1626220": "Royce O'Neale",
        "1627732": "Ben Simmons",
        "1627827": "Dorian Finney-Smith",
        "1628372": "Dennis Smith Jr.",
        "1628969": "Mikal Bridges",
        "1629022": "Lonnie Walker IV",
        "1630549": "Day'Ron Sharpe",
        "1630560": "Cam Thomas"
    },
    "starter_on": "201572|203081|203114|203507|1627736|203915|1627732|1627827|1628969|1630560"
}