{
    "homeTeam": {
        "name": "Jazz",
        "score": 148,
        "logo": "https://cdn.nba.com/logos/nba/1610612762/primary/L/logo.svg"
    },
    "awayTeam": {
        "name": "Pistons",
        "score": 154,
        "logo": "https://cdn.nba.com/logos/nba/1610612765/primary/L/logo.svg"
    },
    "game_id": "22300474",
    "date": "2024-01-03",
    "status": "Final",
    "players": {
        "203482": "Kelly Olynyk",
        "203903": "Jordan Clarkson",
        "1627739": "Kris Dunn",
        "1628374": "Lauri Markkanen",
        "1628381": "John Collins",
        "1629012": "Collin Sexton",
        "1630534": "Ochai Agbaji",
        "1631117": "Walker Kessler",
        "1631323": "Simone Fontecchio",
        "1641718": "Keyonte George",
        "202692": "Alec Burks",
        "202711": "Bojan Bogdanovic",
        "1628995": "Kevin Knox II",
        "1630164": "James Wiseman",
        "1630165": "Killian Hayes",
        "1630587": "Isaiah Livers",
        "1630595": "Cade Cunningham",
        "1631093": "Jaden Ivey",
        "1631105": "Jalen Duren",
        "1641709": "Ausar Thompson"
    },
    "starter_on": "1627739|1628374|1628381|1629012|1631323|202711|1630587|1630595|1631093|1631105"
}