{
    "homeTeam": {
        "name": "Pistons",
        "score": 127,
        "logo": "https://cdn.nba.com/logos/nba/1610612765/primary/L/logo.svg"
    },
    "awayTeam": {
        "name": "Raptors",
        "score": 129,
        "logo": "https://cdn.nba.com/logos/nba/1610612761/primary/L/logo.svg"
    },
    "game_id": "22300440",
    "date": "2023-12-30",
    "status": "Final",
    "players": {
        "201152": "Thaddeus Young",
        "203471": "Dennis Schroder",
        "203490": "Otto Porter Jr.",
        "1627751": "Jakob Poeltl",
        "1627783": "Pascal Siakam",
        "1628449": "Chris Boucher",
        "1629018": "Gary Trent Jr.",
        "1629667": "Jalen McDaniels",
        "1630567": "Scottie Barnes",
        "202692": "Alec Burks",
        "202711": "Bojan Bogdanovic",
        "1628995": "Kevin Knox II",
        "1630164": "James Wiseman",
        "1630165": "Killian Hayes",
        "1630587": "Isaiah Livers",
        "1630595": "Cade Cunningham",
        "1631093": "Jaden Ivey",
        "1631105": "Jalen Duren",
        "1641709": "Ausar Thompson"
    },
    "starter_on": "203471|1627751|1627783|1629018|1630567|202711|1628995|1630595|1631093|1631105"
}