{
    "homeTeam": {
        "name": "Mavericks",
        "score": 134,
        "logo": "https://cdn.nba.com/logos/nba/1610612742/primary/L/logo.svg"
    },
    "awayTeam": {
        "name": "Pacers",
        "score": 127,
        "logo": "https://cdn.nba.com/logos/nba/1610612754/primary/L/logo.svg"
    },
    "game_id": "22400165",
    "date": "2024-11-04",
    "status": "Final",
    "players": {
        "202681": "Kyrie Irving",
        "202691": "Klay Thompson",
        "203915": "Spencer Dinwiddie",
        "203939": "Dwight Powell",
        "1629023": "P.J. Washington",
        "1629029": "Luka Don\u010di\u0107",
        "1629655": "Daniel Gafford",
        "1629656": "Quentin Grimes",
        "1630230": "Naji Marshall",
        "204456": "T.J. McConnell",
        "1626167": "Myles Turner",
        "1627783": "Pascal Siakam",
        "1629614": "Andrew Nembhard",
        "1630167": "Obi Toppin",
        "1630169": "Tyrese Haliburton",
        "1631097": "Bennedict Mathurin",
        "1641716": "Jarace Walker",
        "1641767": "Ben Sheppard"
    },
    "starter_on": "202681|202691|1629023|1629029|1629655|1626167|1627783|1629614|1630169|1631097"
}