{
    "homeTeam": {
        "name": "Wizards",
        "score": 125,
        "logo": "https://cdn.nba.com/logos/nba/1610612764/primary/L/logo.svg"
    },
    "awayTeam": {
        "name": "Hawks",
        "score": 111,
        "logo": "https://cdn.nba.com/logos/nba/1610612737/primary/L/logo.svg"
    },
    "game_id": "22400744",
    "date": "2025-02-08",
    "status": "Final",
    "players": {
        "1626204": "Larry Nance Jr.",
        "1627747": "Caris LeVert",
        "1627777": "Georges Niang",
        "1629027": "Trae Young",
        "1629611": "Terance Mann",
        "1630168": "Onyeka Okongwu",
        "1630249": "Vit Krejci",
        "1630700": "Dyson Daniels",
        "1642258": "Zaccharie Risacher",
        "1626158": "Richaun Holmes",
        "1627763": "Malcolm Brogdon",
        "1629673": "Jordan Poole",
        "1630551": "Justin Champagnie",
        "1630557": "Corey Kispert",
        "1641731": "Bilal Coulibaly",
        "1641774": "Tristan Vukcevic",
        "1641798": "Jaylen Martin",
        "1642267": "Bub Carrington",
        "1642358": "AJ Johnson"
    },
    "starter_on": "1627777|1629027|1630168|1630700|1642258|1626158|1629673|1630551|1641731|1642267"
}