{
    "homeTeam": {
        "name": "Trail Blazers",
        "score": 111,
        "logo": "https://cdn.nba.com/logos/nba/1610612757/primary/L/logo.svg"
    },
    "awayTeam": {
        "name": "Pelicans",
        "score": 102,
        "logo": "https://cdn.nba.com/logos/nba/1610612740/primary/L/logo.svg"
    },
    "game_id": "41700162",
    "date": "2018-04-17",
    "status": "Final",
    "players": {
        "200765": "Rajon Rondo",
        "201950": "Jrue Holiday",
        "202703": "Nikola Mirotic",
        "202734": "E'Twaun Moore",
        "203076": "Anthony Davis",
        "203121": "Darius Miller",
        "203524": "Solomon Hill",
        "203546": "Ian Clark",
        "1627767": "Cheick Diallo",
        "202323": "Evan Turner",
        "202329": "Al-Farouq Aminu",
        "202334": "Ed Davis",
        "203081": "Damian Lillard",
        "203090": "Maurice Harkless",
        "203468": "CJ McCollum",
        "203994": "Jusuf Nurkic",
        "1626192": "Pat Connaughton",
        "1627735": "Wade Baldwin IV",
        "1628380": "Zach Collins"
    },
    "starter_on": "200765|201950|202703|202734|203076|202323|202329|203081|203468|203994"
}